metanetx_post/__init__.py
metanetx_post/_version.py
metanetx_post/helpers.py
metanetx_post/api/__init__.py
metanetx_post/api/helpers.py
metanetx_post/api/compound/__init__.py
metanetx_post/api/compound/kegg.py
metanetx_post/api/compound/pubchem.py
metanetx_post/api/compound/structure.py
metanetx_post/api/reaction/__init__.py
metanetx_post/api/reaction/bigg.py
metanetx_post/api/reaction/expasy.py
metanetx_post/api/reaction/kegg.py
metanetx_post/api/reaction/seed.py
metanetx_post/cli/__init__.py
metanetx_post/cli/helpers.py
metanetx_post/cli/main.py
metanetx_post/cli/compound/__init__.py
metanetx_post/cli/compound/kegg.py
metanetx_post/cli/compound/main.py
metanetx_post/cli/compound/pubchem.py
metanetx_post/cli/compound/structure.py
metanetx_post/cli/reaction/__init__.py
metanetx_post/cli/reaction/bigg.py
metanetx_post/cli/reaction/expasy.py
metanetx_post/cli/reaction/kegg.py
metanetx_post/cli/reaction/main.py
metanetx_post/cli/reaction/seed.py
metanetx_post/etl/__init__.py
metanetx_post/etl/compound.py
metanetx_post/etl/kegg_helpers.py
metanetx_post/etl/reaction/__init__.py
metanetx_post/etl/reaction/expasy.py
metanetx_post/etl/reaction/kegg.py
metanetx_post/model/__init__.py
metanetx_post/model/abstract_molecule_adapter.py
metanetx_post/model/bigg.py
metanetx_post/model/inchi_conflict.py
metanetx_post/model/kegg.py
metanetx_post/model/openbabel_molecule_adapter.py
metanetx_post/model/pubchem.py
metanetx_post/model/rdkit_molecule_adapter.py
metanetx_post/model/seed.py
metanetx_post-0.5.1.dist-info/LICENSE
metanetx_post-0.5.1.dist-info/METADATA
metanetx_post-0.5.1.dist-info/WHEEL
metanetx_post-0.5.1.dist-info/entry_points.txt
metanetx_post-0.5.1.dist-info/top_level.txt
metanetx_post-0.5.1.dist-info/zip-safe
metanetx_post-0.5.1.dist-info/RECORD
