Metadata-Version: 2.1
Name: metanetx-post
Version: 0.5.1
Summary: Enrich the information coming from MetaNetX from additional sources.
Home-page: https://github.com/Midnighter/metanetx-post
Author: Moritz E. Beber
Author-email: midnighter@posteo.net
License: Apache-2.0
Download-URL: https://pypi.org/project/metanetx-post/
Platform: UNKNOWN
Classifier: Development Status :: 2 - Pre-Alpha
Classifier: Intended Audience :: Science/Research
Classifier: License :: OSI Approved :: Apache Software License
Classifier: Natural Language :: English
Classifier: Operating System :: MacOS :: MacOS X
Classifier: Operating System :: Microsoft :: Windows :: Windows 10
Classifier: Operating System :: POSIX
Classifier: Programming Language :: Python :: 3.8
Classifier: Programming Language :: Python :: 3 :: Only
Classifier: Topic :: Scientific/Engineering :: Bio-Informatics
Requires-Python: >=3.8
Requires-Dist: aioftp (~=0.13)
Requires-Dist: Click (~=7.0)
Requires-Dist: click-log (~=0.3)
Requires-Dist: cobra-component-models (~=0.5)
Requires-Dist: depinfo (~=1.5)
Requires-Dist: httpx (~=0.11)
Requires-Dist: metanetx-assets (~=0.2)
Requires-Dist: metanetx-sdk (~=0.5)
Requires-Dist: pandas (~=1.0)
Requires-Dist: pydantic (~=1.4)
Requires-Dist: pyparsing (~=2.4)
Requires-Dist: rdflib (~=4.2)
Requires-Dist: SQLAlchemy (~=1.3)
Requires-Dist: tqdm (~=4.0)
Provides-Extra: development
Requires-Dist: black ; extra == 'development'
Requires-Dist: isort ; extra == 'development'
Requires-Dist: tox ; extra == 'development'
Provides-Extra: openbabel
Requires-Dist: openbabel (~=3.0) ; extra == 'openbabel'
Provides-Extra: rdkit
Requires-Dist: rdkit ; extra == 'rdkit'
